superrec2/__init__.py
superrec2/cli/__main__.py
superrec2/cli/draw.py
superrec2/cli/reconcile.py
superrec2/cli/util.py
superrec2/compute/__init__.py
superrec2/compute/exhaustive.py
superrec2/compute/reconciliation.py
superrec2/compute/super_reconciliation.py
superrec2/compute/unordered_super_reconciliation.py
superrec2/model/__init__.py
superrec2/model/history.py
superrec2/model/reconciliation.py
superrec2/model/synteny.py
superrec2/model/tree_mapping.py
superrec2/render/__init__.py
superrec2/render/layout.py
superrec2/render/model.py
superrec2/render/tikz.py
superrec2/utils/__init__.py
superrec2/utils/disjoint_set.py
superrec2/utils/dynamic_programming.py
superrec2/utils/file.py
superrec2/utils/geometry.py
superrec2/utils/range_min_query.py
superrec2/utils/subsequences.py
superrec2/utils/tex.py
superrec2/utils/text.py
superrec2/utils/toposort.py
superrec2/utils/trees.py
superrec2-0.1.0.dist-info/METADATA
superrec2-0.1.0.dist-info/WHEEL
superrec2-0.1.0.dist-info/entry_points.txt
superrec2-0.1.0.dist-info/licenses/LICENSE
superrec2-0.1.0.dist-info/RECORD
