Metadata-Version: 2.1
Name: superrec2
Version: 0.1.0
Summary: Run and compare algorithms for phylogenetic reconciliation and super-reconciliation
Project-URL: Homepage, https://github.com/UdeM-LBIT/superrec2
Project-URL: Bug Tracker, https://github.com/UdeM-LBIT/superrec2/issues
Author-email: Mattéo Delabre <git.matteo@delab.re>
License-File: LICENSE
Classifier: License :: OSI Approved :: GNU General Public License v3 or later (GPLv3+)
Classifier: Operating System :: OS Independent
Classifier: Programming Language :: Python :: 3
Requires-Python: >=3.11
Requires-Dist: ete3
Requires-Dist: infinity
Requires-Dist: numpy
Requires-Dist: six
Requires-Dist: tqdm
